src/__init__.py
src/clipstudio.py
clip_studio_paint_layers_extractor-0.1.0.dist-info/LICENSE
clip_studio_paint_layers_extractor-0.1.0.dist-info/METADATA
clip_studio_paint_layers_extractor-0.1.0.dist-info/WHEEL
clip_studio_paint_layers_extractor-0.1.0.dist-info/RECORD
