Metadata-Version: 2.1
Name: clip-studio-paint-layers-extractor
Version: 0.1.0
Summary: A Python library to extract and manipulate Clip Studio Paint (.clip) files
Home-page: https://github.com/FlagCatStudio/clip-studio-paint-layers-extractor
License: MIT
Keywords: clip studio paint,layers,python
Author: coolstorybro
Author-email: quentin@flagcat.studio
Requires-Python: >=3.12,<4.0
Classifier: License :: OSI Approved :: MIT License
Classifier: Programming Language :: Python :: 3
Classifier: Programming Language :: Python :: 3.12
Requires-Dist: pillow (>=11.0.0,<12.0.0)
Project-URL: Repository, https://github.com/FlagCatStudio/clip-studio-paint-layers-extractor
